[
  {
    "run_id": "3ee5e69bccbb",
    "generated_at": "2026-07-03T12:34:24.258083+00:00",
    "summary": {
      "total_leads": 31,
      "hot_leads": 25,
      "warm_leads": 6,
      "contactable": 0,
      "with_whatsapp": 0,
      "with_phone": 0,
      "avg_score": 65.8,
      "avg_score_hot": 70.4,
      "conversion_probability": 80.6,
      "by_category": {
        "TRANSFER_PROBLEM": 10,
        "FINE_DISPUTE": 19,
        "DOCUMENTATION_ISSUE": 2
      },
      "by_platform": {
        "Reddit": 31
      },
      "by_province": {
        "Córdoba": 2,
        "CABA": 5,
        "Salta": 2,
        "Entre Ríos": 1
      }
    }
  },
  {
    "run_id": "0d0317d8d2f1",
    "generated_at": "2026-07-03T18:58:58.307339+00:00",
    "summary": {
      "total_leads": 20,
      "hot_leads": 18,
      "warm_leads": 2,
      "contactable": 0,
      "with_whatsapp": 0,
      "with_phone": 0,
      "avg_score": 70.0,
      "avg_score_hot": 72.8,
      "conversion_probability": 90.0,
      "by_category": {
        "TRANSFER_PROBLEM": 10,
        "FINE_DISPUTE": 10
      },
      "by_platform": {
        "Reddit": 20
      },
      "by_province": {
        "Córdoba": 1,
        "CABA": 2,
        "Salta": 1
      }
    }
  }
]