{"httpProtocol":"HTTP/1.1","clientAcceptEncoding":"gzip, deflate, br","requestPriority":"","edgeRequestKeepAliveStatus":1,"requestHeaderNames":{},"clientTcpRtt":6,"clientQuicRtt":0,"colo":"HKG","asn":45102,"asOrganization":"Alibaba Cloud - HK","country":"HK","isEUCountry":false,"city":"Hong Kong","continent":"AS","timezone":"Asia/Hong_Kong","longitude":"114.17469","latitude":"22.27832","postalCode":"999077","tlsVersion":"TLSv1.3","tlsCipher":"AEAD-AES256-GCM-SHA384","tlsClientRandom":"HE8rprpeS2UaOjKXhVFnfREIsYl0M3r1sGGkjoYwcsA=","tlsClientCiphersSha1":"kXrN3VEKDdzz2cPKTQaKzpxVTxQ=","tlsClientExtensionsSha1":"1eY97BUYYO8vDaTfHQywB1pcNdM=","tlsClientExtensionsSha1Le":"u4wtEMFQBY18l3BzHAvORm+KGRw=","tlsExportedAuthenticator":{"clientHandshake":"1d3ffef385ef69251ec1031ea069028ec4fc47e65384249dab2bb8077de75f95cbd64fc81e55f6aa0c1b8f5c1adf5b55","serverHandshake":"887c93c455bef21b66583a9489d6af706204841d12a135ddc4798322b79a8f6abbe336ab974ef2d1830fabed16880a70","clientFinished":"a4555eedc04d8fd501d49b0f099f17d1ad26d4c86b6b226900cf91932d3140d2c77f58436bc602096ffcb60bfbb4148b","serverFinished":"bfdbd3bb133ea066cf7b1640eda5b4c065a1fa41f8bd594e627f910e9093fa2feced7a35b0cec6ac1c097683a5a2bd73"},"tlsClientHelloLength":"1605","tlsClientAuth":{"certPresented":"0","certVerified":"NONE","certRevoked":"0","certIssuerDN":"","certSubjectDN":"","certIssuerDNRFC2253":"","certSubjectDNRFC2253":"","certIssuerDNLegacy":"","certSubjectDNLegacy":"","certSerial":"","certIssuerSerial":"","certSKI":"","certIssuerSKI":"","certFingerprintSHA1":"","certFingerprintSHA256":"","certNotBefore":"","certNotAfter":"","certRFC9440":"","certRFC9440TooLarge":false,"certChainRFC9440":"","certChainRFC9440TooLarge":false},"verifiedBotCategory":"","edgeL4":{"deliveryRate":703101},"botManagement":{"corporateProxy":false,"verifiedBot":false,"jsDetection":{"passed":false},"staticResource":false,"detectionIds":{},"score":99}}